pushkin/__init__.py
pushkin/test.py
pushkin/classify/__init__.py
pushkin/classify/classify.py
pushkin/train/__init__.py
pushkin/train/train.py
mlpushkin-0.1.dist-info/LICENSE
mlpushkin-0.1.dist-info/METADATA
mlpushkin-0.1.dist-info/WHEEL
mlpushkin-0.1.dist-info/top_level.txt
mlpushkin-0.1.dist-info/RECORD
